{"name":"运维","slug":"运维","count":1,"postlist":[{"title":"Mysql离线安装","uid":"cc28c8e7df72b9e1dcfbf18f5ae2769e","slug":"Mysql离线安装","date":"2019-07-08T07:26:09.000Z","updated":"2021-07-08T07:31:46.870Z","comments":true,"path":"api/articles/Mysql离线安装.json","keywords":null,"cover":"/images/3.jpg","text":" 前言因为部分原因，内网不能连上互联网，所以环境搭建只能使用离线安装的方法。在此记录一下mysql的5.7的离线安装。 MYSQL5.7版本基础环境安装首先将系统自带的mariadb删除 [root@localhost &#x2F;]# rpm -qa |grep mariadb...","link":"","photos":[],"count_time":{"symbolsCount":"9.9k","symbolsTime":"9 mins."},"categories":[{"name":"运维","slug":"运维","count":1,"path":"api/categories/运维.json"}],"tags":[{"name":"运维","slug":"运维","count":1,"path":"api/tags/运维.json"}],"author":{"name":"96loveslife","slug":"blog-author","avatar":"/images/logo.jpg","link":"/","description":"为什么有一些人放屁可以放很大声? </br></br></br> <b>因为他可能穿了喇叭裤</b>","socials":{"github":"https://github.com/96loveslife","twitter":"","stackoverflow":"","wechat":"","qq":"","weibo":"","zhihu":"","csdn":"","juejin":"","customs":{}}},"feature":true}]}